int_hash_lib/__init__.py
int_hash_lib/utils/__init__.py
int_hash_lib/utils/default.py
int_hash_lib/utils/email.py
int_hash_lib/utils/ip_address.py
int_hash_lib/utils/normalizer.py
int_hash_lib/utils/phone.py
int_hash_lib/utils/user_agent.py
int_hash_lib-0.0.15.dist-info/METADATA
int_hash_lib-0.0.15.dist-info/WHEEL
int_hash_lib-0.0.15.dist-info/top_level.txt
int_hash_lib-0.0.15.dist-info/RECORD
